django_sage_model_generator/__init__.py
django_sage_model_generator/core/__init__.py
django_sage_model_generator/core/handlers.py
django_sage_model_generator/core/parser.py
django_sage_model_generator/core/settings.py
django_sage_model_generator/core/utils.py
django_sage_model_generator/helper/__init__.py
django_sage_model_generator/helper/dataclasses.py
django_sage_model_generator/helper/design.py
django_sage_model_generator/helper/enums.py
django_sage_model_generator/helper/filter.py
django_sage_model_generator/root/auth/__init__.py
django_sage_model_generator/root/auth/group.py
django_sage_model_generator/root/auth/user.py
django_sage_model_generator/root/auth/usergroup.py
django_sage_model_generator/root/awareness/__init__.py
django_sage_model_generator/root/awareness/notification.py
django_sage_model_generator/root/awareness/usernotification.py
django_sage_model_generator/root/bankportal.py
django_sage_model_generator/root/bundleinteraction.py
django_sage_model_generator/root/bundleparticipation.py
django_sage_model_generator/root/gamification/__init__.py
django_sage_model_generator/root/gamification/badge.py
django_sage_model_generator/root/gamification/certificate.py
django_sage_model_generator/root/gamification/userbadge.py
django_sage_model_generator/root/gamification/usercertificate.py
django_sage_model_generator/root/gamification/userprofile.py
django_sage_model_generator/root/helpers/choices.py
django_sage_model_generator/root/practiceinteraction.py
django_sage_model_generator/root/practiceparticipation.py
django_sage_model_generator/root/projectparticipation.py
django_sage_model_generator/root/saas/__init__.py
django_sage_model_generator/root/saas/offer.py
django_sage_model_generator/root/saas/plan.py
django_sage_model_generator/root/saas/planoption.py
django_sage_model_generator/root/saas/planoptionincluded.py
django_sage_model_generator/root/saas/subscription.py
django_sage_model_generator/root/saas/subscriptionplaninvoice.py
django_sage_model_generator-0.1.0.dist-info/LICENSE
django_sage_model_generator-0.1.0.dist-info/METADATA
django_sage_model_generator-0.1.0.dist-info/WHEEL
django_sage_model_generator-0.1.0.dist-info/RECORD
